strongmind_deployment/__init__.py
strongmind_deployment/acm.py
strongmind_deployment/alb.py
strongmind_deployment/autotag.py
strongmind_deployment/batch.py
strongmind_deployment/cloudfront.py
strongmind_deployment/container.py
strongmind_deployment/dashboard.py
strongmind_deployment/dynamo.py
strongmind_deployment/execution.py
strongmind_deployment/lambda_component.py
strongmind_deployment/operations.py
strongmind_deployment/rails.py
strongmind_deployment/redis.py
strongmind_deployment/route53_zone.py
strongmind_deployment/secrets.py
strongmind_deployment/sm_vpc.py
strongmind_deployment/storage.py
strongmind_deployment/subnet.py
strongmind_deployment/taggable.py
strongmind_deployment/util.py
strongmind_deployment/vpc.py
strongmind_deployment/worker_autoscale.py
strongmind_deployment-1.1.291.dist-info/METADATA
strongmind_deployment-1.1.291.dist-info/WHEEL
strongmind_deployment-1.1.291.dist-info/licenses/LICENSE
strongmind_deployment-1.1.291.dist-info/RECORD
