Metadata-Version: 2.4
Name: strongmind_deployment
Version: 1.1.291
Summary: Deployment tools for Strongmind
Project-URL: Homepage, https://github.com/strongmind/public-reusable-workflows/tree/main/deployment
Author-email: Belding <teambelding@strongmind.com>
License-File: LICENSE
Classifier: License :: OSI Approved :: MIT License
Classifier: Operating System :: OS Independent
Classifier: Programming Language :: Python :: 3
Requires-Python: >=3.9
Requires-Dist: boto3
Requires-Dist: pulumi
Requires-Dist: pulumi-aws
Requires-Dist: pulumi-awsx
Requires-Dist: pulumi-random
